[ 
    { "name": "Tanglewood - Guess Correctly" },
    { "name": "Tanglewood - Bone" }, 
    { "name": "Tanglewood - Cursed Object" }, 
    { "name": "Ridgeview - Guess Correctly" },
    { "name": "Ridgeview - Bone" },
    { "name": "Ridgeview - Cursed Object" }, 
    { "name": "Bleasdale - Guess Correctly" },
    { "name": "Bleasdale - Bone" },
    { "name": "Bleasdale - Cursed Object" },
    { "name": "Grafton - Guess Correctly" },
    { "name": "Grafton - Bone" },
    { "name": "Grafton - Cursed Object" },
    { "name": "Edgefield - Guess Correctly" },
    { "name": "Edgefield - Bone" },
    { "name": "Edgefield - Cursed Object" },
    { "name": "Willow - Guess Correctly" },
    { "name": "Willow - Bone" },
    { "name": "Willow - Cursed Object" },
    { "name": "Prison - Guess Correctly", "requires": ["Weak Flashlight", "Smudge Sticks"] },
    { "name": "Prison - Bone", "requires": ["Weak Flashlight", "Smudge Sticks"] },
    { "name": "Prison - Cursed Object", "requires": ["Weak Flashlight", "Smudge Sticks"] },
    { "name": "High School - Guess Correctly", "requires": ["Weak Flashlight", "Smudge Sticks"] },
    { "name": "High School - Bone", "requires": ["Weak Flashlight", "Smudge Sticks"] },
    { "name": "High School - Cursed Object", "requires": ["Weak Flashlight", "Smudge Sticks"] },
    { "name": "Asylum - Guess Correctly", "requires": ["Weak Flashlight", "Smudge Sticks"] },
    { "name": "Asylum - Bone", "requires": ["Weak Flashlight", "Smudge Sticks"] },
    { "name": "Asylum - Cursed Object", "requires": ["Weak Flashlight", "Smudge Sticks"] },
    { "name": "Maple Lodge - Guess Correctly", "requires": ["Weak Flashlight", "Smudge Sticks"] },
    { "name": "Maple Lodge - Bone", "requires": ["Weak Flashlight", "Smudge Sticks"] },
    { "name": "Maple Lodge - Cursed Object", "requires": ["Weak Flashlight", "Smudge Sticks"] }
]